nudatus.py
nudatus-0.0.5.dist-info/AUTHORS
nudatus-0.0.5.dist-info/LICENSE
nudatus-0.0.5.dist-info/METADATA
nudatus-0.0.5.dist-info/WHEEL
nudatus-0.0.5.dist-info/entry_points.txt
nudatus-0.0.5.dist-info/top_level.txt
nudatus-0.0.5.dist-info/RECORD
