Metadata-Version: 2.1
Name: nudatus
Version: 0.0.5
Summary: Strip comments from scripts, intended for use with MicroPython and other storage constrained environments
Home-page: https://github.com/zanderbrown/nudatus
Author: Zander Brown
License: MIT
Platform: UNKNOWN
Classifier: Development Status :: 4 - Beta
Classifier: Environment :: Console
Classifier: Intended Audience :: Developers
Classifier: License :: OSI Approved :: MIT License
Classifier: Operating System :: POSIX
Classifier: Operating System :: Microsoft :: Windows
Classifier: Programming Language :: Python :: 3.5
Requires-Python: >=3.5
Provides-Extra: all
Requires-Dist: black ; extra == 'all'
Requires-Dist: coverage ; extra == 'all'
Requires-Dist: pytest-faulthandler ; extra == 'all'
Requires-Dist: pytest (>=4.6) ; extra == 'all'
Requires-Dist: wheel ; extra == 'all'
Requires-Dist: twine ; extra == 'all'
Requires-Dist: pytest-random-order (>=1.0.0) ; extra == 'all'
Requires-Dist: pytest-cov ; extra == 'all'
Provides-Extra: dev
Requires-Dist: pytest (>=4.6) ; extra == 'dev'
Requires-Dist: pytest-cov ; extra == 'dev'
Requires-Dist: pytest-random-order (>=1.0.0) ; extra == 'dev'
Requires-Dist: pytest-faulthandler ; extra == 'dev'
Requires-Dist: coverage ; extra == 'dev'
Requires-Dist: black ; extra == 'dev'
Requires-Dist: wheel ; extra == 'dev'
Requires-Dist: twine ; extra == 'dev'
Provides-Extra: package
Requires-Dist: wheel ; extra == 'package'
Requires-Dist: twine ; extra == 'package'
Provides-Extra: tests
Requires-Dist: pytest (>=4.6) ; extra == 'tests'
Requires-Dist: pytest-cov ; extra == 'tests'
Requires-Dist: pytest-random-order (>=1.0.0) ; extra == 'tests'
Requires-Dist: pytest-faulthandler ; extra == 'tests'
Requires-Dist: coverage ; extra == 'tests'
Requires-Dist: black ; extra == 'tests'
